{
  "players": [
    {
      "rank": 5275709,
      "name": 1577521286,
      "pts": 637,
      "villages": 109
    },
    {
      "rank": 4700271,
      "name": 1577261814,
      "pts": 605,
      "villages": 194
    },
    {
      "rank": 4520590,
      "name": 1576654562,
      "pts": 607,
      "villages": 194
    },
    {
      "rank": 4347580,
      "name": 1577254525,
      "pts": 514,
      "villages": 194
    },
    {
      "rank": 3882397,
      "name": 1576800489,
      "pts": 644,
      "villages": 43
    },
    {
      "rank": 3707466,
      "name": 9857437,
      "pts": 441,
      "villages": 194
    },
    {
      "rank": 3489274,
      "name": 677000,
      "pts": 401,
      "villages": 109
    },
    {
      "rank": 3223883,
      "name": 1577484474,
      "pts": 427,
      "villages": 194
    },
    {
      "rank": 3200763,
      "name": 1577498428,
      "pts": 439,
      "villages": 194
    },
    {
      "rank": 2918352,
      "name": 1577490480,
      "pts": 370,
      "villages": 109
    },
    {
      "rank": 2872915,
      "name": 1577484423,
      "pts": 337,
      "villages": 194
    },
    {
      "rank": 2613542,
      "name": 1576173553,
      "pts": 289,
      "villages": 43
    },
    {
      "rank": 2397998,
      "name": 1577360921,
      "pts": 317,
      "villages": 194
    },
    {
      "rank": 2297212,
      "name": 1577241684,
      "pts": 306,
      "villages": 194
    },
    {
      "rank": 2132482,
      "name": 10172436,
      "pts": 251,
      "villages": 109
    },
    {
      "rank": 2102145,
      "name": 8319911,
      "pts": 284,
      "villages": 194
    },
    {
      "rank": 2063798,
      "name": 1577004394,
      "pts": 277,
      "villages": 194
    },
    {
      "rank": 2061186,
      "name": 1576962937,
      "pts": 262,
      "villages": 109
    },
    {
      "rank": 2051356,
      "name": 1577122437,
      "pts": 276,
      "villages": 624
    },
    {
      "rank": 2051091,
      "name": 1577390012,
      "pts": 287,
      "villages": 109
    },
    {
      "rank": 2031170,
      "name": 2857509,
      "pts": 267,
      "villages": 109
    },
    {
      "rank": 2018457,
      "name": 1577283332,
      "pts": 247,
      "villages": 109
    },
    {
      "rank": 1936683,
      "name": 591854,
      "pts": 356,
      "villages": 624
    },
    {
      "rank": 1925825,
      "name": 1577497670,
      "pts": 266,
      "villages": 624
    },
    {
      "rank": 1874633,
      "name": 1577102282,
      "pts": 215,
      "villages": 109
    },
    {
      "rank": 1871090,
      "name": 1577499169,
      "pts": 228,
      "villages": 43
    },
    {
      "rank": 1855809,
      "name": 1577273211,
      "pts": 302,
      "villages": 194
    },
    {
      "rank": 1843321,
      "name": 1576154840,
      "pts": 278,
      "villages": 194
    },
    {
      "rank": 1759753,
      "name": 1577463038,
      "pts": 223,
      "villages": 624
    },
    {
      "rank": 1699485,
      "name": 8502049,
      "pts": 184,
      "villages": 109
    },
    {
      "rank": 1694902,
      "name": 1577380798,
      "pts": 223,
      "villages": 109
    },
    {
      "rank": 1673548,
      "name": 1577492544,
      "pts": 274,
      "villages": 194
    },
    {
      "rank": 1664643,
      "name": 1577274339,
      "pts": 222,
      "villages": 43
    },
    {
      "rank": 1657268,
      "name": 2692451,
      "pts": 212,
      "villages": 194
    },
    {
      "rank": 1634164,
      "name": 10172239,
      "pts": 219,
      "villages": 43
    },
    {
      "rank": 1606637,
      "name": 9714776,
      "pts": 235,
      "villages": 109
    },
    {
      "rank": 1602173,
      "name": 1576658950,
      "pts": 191,
      "villages": 624
    },
    {
      "rank": 1581114,
      "name": 1577498770,
      "pts": 206,
      "villages": 43
    },
    {
      "rank": 1578669,
      "name": 1577054572,
      "pts": 219,
      "villages": 624
    },
    {
      "rank": 1536416,
      "name": 1577385945,
      "pts": 271,
      "villages": 108
    },
    {
      "rank": 1520799,
      "name": 1576164170,
      "pts": 225,
      "villages": 194
    },
    {
      "rank": 1511873,
      "name": 9642632,
      "pts": 201,
      "villages": 194
    },
    {
      "rank": 1477908,
      "name": 9147907,
      "pts": 172,
      "villages": 194
    },
    {
      "rank": 1473427,
      "name": 9955195,
      "pts": 200,
      "villages": 108
    },
    {
      "rank": 1462001,
      "name": 1577486006,
      "pts": 193,
      "villages": 43
    },
    {
      "rank": 1414363,
      "name": 1577521768,
      "pts": 191,
      "villages": 194
    },
    {
      "rank": 1408586,
      "name": 1576620804,
      "pts": 234,
      "villages": 109
    },
    {
      "rank": 1398844,
      "name": 1576596873,
      "pts": 160,
      "villages": 109
    },
    {
      "rank": 1391256,
      "name": 8927127,
      "pts": 192,
      "villages": 109
    },
    {
      "rank": 1389796,
      "name": 8942925,
      "pts": 207,
      "villages": 0
    }
  ],
  "tribes": [
    {
      "rank": 54499215,
      "name": 194,
      "tag": "Squirtle Squad",
      "pts": 25,
      "villages": 54499215
    },
    {
      "rank": 43108465,
      "name": 109,
      "tag": "Uri Nation",
      "pts": 25,
      "villages": 43108465
    },
    {
      "rank": 26477712,
      "name": 43,
      "tag": "Rebel",
      "pts": 25,
      "villages": 26477712
    },
    {
      "rank": 18764631,
      "name": 624,
      "tag": "Level 8",
      "pts": 18,
      "villages": 18764631
    },
    {
      "rank": 11429143,
      "name": 108,
      "tag": "UNBELIEBT",
      "pts": 24,
      "villages": 11429143
    },
    {
      "rank": 11299005,
      "name": 430,
      "tag": "Bisa Bash",
      "pts": 22,
      "villages": 11299005
    },
    {
      "rank": 5086173,
      "name": 124,
      "tag": "Sonne",
      "pts": 21,
      "villages": 5086173
    },
    {
      "rank": 4829764,
      "name": 619,
      "tag": "Die Blasenpolizei",
      "pts": 22,
      "villages": 4829764
    },
    {
      "rank": 3741711,
      "name": 67,
      "tag": "Wallstreet",
      "pts": 23,
      "villages": 3741711
    },
    {
      "rank": 3426551,
      "name": 482,
      "tag": "Varkuun",
      "pts": 21,
      "villages": 3426551
    },
    {
      "rank": 3604250,
      "name": 360,
      "tag": "Sonne²",
      "pts": 20,
      "villages": 3604250
    },
    {
      "rank": 3065169,
      "name": 75,
      "tag": "Phoenix",
      "pts": 22,
      "villages": 3065169
    },
    {
      "rank": 3037350,
      "name": 22,
      "tag": "Schattenkonzil",
      "pts": 20,
      "villages": 3037350
    },
    {
      "rank": 2291195,
      "name": 605,
      "tag": "Orden der Morgenröte",
      "pts": 21,
      "villages": 2291195
    },
    {
      "rank": 2222956,
      "name": 333,
      "tag": "OhneWitz",
      "pts": 25,
      "villages": 2222956
    },
    {
      "rank": 2764836,
      "name": 356,
      "tag": "Runenwölfe",
      "pts": 17,
      "villages": 2764836
    },
    {
      "rank": 2165301,
      "name": 475,
      "tag": "Party Time",
      "pts": 20,
      "villages": 2165301
    },
    {
      "rank": 2078759,
      "name": 65,
      "tag": "Level7",
      "pts": 24,
      "villages": 2078759
    },
    {
      "rank": 1868812,
      "name": 558,
      "tag": "Dashing Dachshound",
      "pts": 11,
      "villages": 1868812
    },
    {
      "rank": 1403681,
      "name": 777,
      "tag": "Non Player Character II",
      "pts": 25,
      "villages": 1403681
    },
    {
      "rank": 2014002,
      "name": 18,
      "tag": "Gladiatoren",
      "pts": 20,
      "villages": 2014002
    },
    {
      "rank": 1422940,
      "name": 780,
      "tag": "die mutigen Mungos",
      "pts": 25,
      "villages": 1422940
    },
    {
      "rank": 1110148,
      "name": 980,
      "tag": "Vorsicht Gummibärchen",
      "pts": 18,
      "villages": 1110148
    },
    {
      "rank": 1313842,
      "name": 431,
      "tag": "Warriors of the World",
      "pts": 20,
      "villages": 1313842
    },
    {
      "rank": 1640619,
      "name": 739,
      "tag": "UNTRAGBAR",
      "pts": 18,
      "villages": 1640619
    },
    {
      "rank": 1309622,
      "name": 1167,
      "tag": "Der neue Stamm",
      "pts": 17,
      "villages": 1309622
    },
    {
      "rank": 1320104,
      "name": 144,
      "tag": "Working Class",
      "pts": 23,
      "villages": 1320104
    },
    {
      "rank": 1178279,
      "name": 879,
      "tag": "Wallstreet2",
      "pts": 18,
      "villages": 1178279
    },
    {
      "rank": 603962,
      "name": 1165,
      "tag": "OhneWitz2",
      "pts": 24,
      "villages": 603962
    },
    {
      "rank": 708718,
      "name": 820,
      "tag": "Schalke Hooligans",
      "pts": 22,
      "villages": 708718
    },
    {
      "rank": 688332,
      "name": 688,
      "tag": "Last Knights",
      "pts": 23,
      "villages": 688332
    },
    {
      "rank": 844288,
      "name": 699,
      "tag": "Originals",
      "pts": 19,
      "villages": 844288
    },
    {
      "rank": 601265,
      "name": 1033,
      "tag": "Olymp",
      "pts": 21,
      "villages": 601265
    },
    {
      "rank": 660885,
      "name": 1001,
      "tag": "Rhein-Neckar Orden",
      "pts": 25,
      "villages": 660885
    },
    {
      "rank": 631246,
      "name": 509,
      "tag": "MGZR",
      "pts": 15,
      "villages": 631246
    },
    {
      "rank": 591872,
      "name": 847,
      "tag": "Warrior",
      "pts": 20,
      "villages": 591872
    },
    {
      "rank": 592827,
      "name": 994,
      "tag": "Working Class ²",
      "pts": 16,
      "villages": 592827
    },
    {
      "rank": 545666,
      "name": 1042,
      "tag": "Level6",
      "pts": 12,
      "villages": 545666
    },
    {
      "rank": 668635,
      "name": 479,
      "tag": "Tote Lügen Nicht+",
      "pts": 13,
      "villages": 668635
    },
    {
      "rank": 938237,
      "name": 98,
      "tag": "OldMen",
      "pts": 18,
      "villages": 938237
    },
    {
      "rank": 503805,
      "name": 858,
      "tag": "Orden der Templer",
      "pts": 17,
      "villages": 503805
    },
    {
      "rank": 652865,
      "name": 729,
      "tag": "Projekt Brot und Brötchen",
      "pts": 17,
      "villages": 652865
    },
    {
      "rank": 579733,
      "name": 201,
      "tag": "Die sturen Westfalen",
      "pts": 18,
      "villages": 579733
    },
    {
      "rank": 658681,
      "name": 462,
      "tag": "Rebell",
      "pts": 10,
      "villages": 658681
    },
    {
      "rank": 707750,
      "name": 988,
      "tag": "We are Legends",
      "pts": 10,
      "villages": 707750
    },
    {
      "rank": 427137,
      "name": 962,
      "tag": "Los Nablos",
      "pts": 17,
      "villages": 427137
    },
    {
      "rank": 574323,
      "name": 788,
      "tag": "Project X",
      "pts": 10,
      "villages": 574323
    },
    {
      "rank": 674549,
      "name": 2,
      "tag": "The Incredible",
      "pts": 19,
      "villages": 674549
    },
    {
      "rank": 420787,
      "name": 843,
      "tag": "TheOutlaws",
      "pts": 19,
      "villages": 420787
    },
    {
      "rank": 387719,
      "name": 1019,
      "tag": "F*** Around and Find Out",
      "pts": 17,
      "villages": 387719
    }
  ]
}