{
  "players": [
    {
      "rank": 26377904,
      "name": 8092491,
      "pts": 2172,
      "villages": 45
    },
    {
      "rank": 24334681,
      "name": 919837538,
      "pts": 2173,
      "villages": 1417
    },
    {
      "rank": 19731278,
      "name": 919434669,
      "pts": 1502,
      "villages": 45
    },
    {
      "rank": 17632665,
      "name": 6422318,
      "pts": 1434,
      "villages": 45
    },
    {
      "rank": 16837397,
      "name": 7166493,
      "pts": 1347,
      "villages": 45
    },
    {
      "rank": 15475611,
      "name": 919346207,
      "pts": 1283,
      "villages": 45
    },
    {
      "rank": 15347590,
      "name": 919659588,
      "pts": 1334,
      "villages": 45
    },
    {
      "rank": 15310885,
      "name": 919860449,
      "pts": 1301,
      "villages": 45
    },
    {
      "rank": 15048598,
      "name": 1361136,
      "pts": 1249,
      "villages": 45
    },
    {
      "rank": 14945708,
      "name": 6085300,
      "pts": 1202,
      "villages": 45
    },
    {
      "rank": 14842619,
      "name": 919390038,
      "pts": 1181,
      "villages": 45
    },
    {
      "rank": 14618514,
      "name": 919580274,
      "pts": 1225,
      "villages": 45
    },
    {
      "rank": 14456936,
      "name": 7928191,
      "pts": 1208,
      "villages": 45
    },
    {
      "rank": 14274301,
      "name": 919619983,
      "pts": 1197,
      "villages": 45
    },
    {
      "rank": 14224350,
      "name": 919866147,
      "pts": 1281,
      "villages": 45
    },
    {
      "rank": 13987719,
      "name": 919344978,
      "pts": 1191,
      "villages": 45
    },
    {
      "rank": 13917541,
      "name": 919864891,
      "pts": 1177,
      "villages": 45
    },
    {
      "rank": 13228292,
      "name": 919551372,
      "pts": 1150,
      "villages": 45
    },
    {
      "rank": 13026987,
      "name": 171892,
      "pts": 1057,
      "villages": 45
    },
    {
      "rank": 12981032,
      "name": 919783476,
      "pts": 1079,
      "villages": 45
    },
    {
      "rank": 12756125,
      "name": 707128,
      "pts": 1051,
      "villages": 45
    },
    {
      "rank": 12746638,
      "name": 5495724,
      "pts": 1111,
      "villages": 45
    },
    {
      "rank": 12579898,
      "name": 919858565,
      "pts": 1039,
      "villages": 45
    },
    {
      "rank": 12372306,
      "name": 919626659,
      "pts": 1077,
      "villages": 190
    },
    {
      "rank": 12347001,
      "name": 8259125,
      "pts": 1024,
      "villages": 45
    },
    {
      "rank": 12245275,
      "name": 919834361,
      "pts": 1021,
      "villages": 95
    },
    {
      "rank": 12023385,
      "name": 919694385,
      "pts": 1013,
      "villages": 45
    },
    {
      "rank": 11752160,
      "name": 919685196,
      "pts": 976,
      "villages": 45
    },
    {
      "rank": 11746131,
      "name": 5295749,
      "pts": 969,
      "villages": 45
    },
    {
      "rank": 11690149,
      "name": 919574579,
      "pts": 1035,
      "villages": 45
    },
    {
      "rank": 11690117,
      "name": 919393296,
      "pts": 984,
      "villages": 45
    },
    {
      "rank": 11660344,
      "name": 919671987,
      "pts": 1001,
      "villages": 190
    },
    {
      "rank": 11522832,
      "name": 919511204,
      "pts": 1013,
      "villages": 45
    },
    {
      "rank": 11439199,
      "name": 918707943,
      "pts": 958,
      "villages": 45
    },
    {
      "rank": 11402004,
      "name": 919507006,
      "pts": 1049,
      "villages": 45
    },
    {
      "rank": 11191631,
      "name": 6665293,
      "pts": 1054,
      "villages": 45
    },
    {
      "rank": 11083989,
      "name": 7251297,
      "pts": 951,
      "villages": 95
    },
    {
      "rank": 11066680,
      "name": 919626393,
      "pts": 933,
      "villages": 45
    },
    {
      "rank": 11056448,
      "name": 919453825,
      "pts": 926,
      "villages": 45
    },
    {
      "rank": 10972676,
      "name": 919623858,
      "pts": 972,
      "villages": 45
    },
    {
      "rank": 10865266,
      "name": 919600011,
      "pts": 896,
      "villages": 45
    },
    {
      "rank": 10270408,
      "name": 388517,
      "pts": 851,
      "villages": 190
    },
    {
      "rank": 10044626,
      "name": 919658417,
      "pts": 843,
      "villages": 95
    },
    {
      "rank": 9970953,
      "name": 919655458,
      "pts": 846,
      "villages": 45
    },
    {
      "rank": 9826941,
      "name": 2117689,
      "pts": 852,
      "villages": 45
    },
    {
      "rank": 9821118,
      "name": 919725219,
      "pts": 992,
      "villages": 45
    },
    {
      "rank": 9801808,
      "name": 5307209,
      "pts": 970,
      "villages": 45
    },
    {
      "rank": 9696783,
      "name": 7942210,
      "pts": 845,
      "villages": 190
    },
    {
      "rank": 9460546,
      "name": 6701185,
      "pts": 790,
      "villages": 45
    },
    {
      "rank": 9447205,
      "name": 919861757,
      "pts": 792,
      "villages": 1374
    }
  ],
  "tribes": [
    {
      "rank": 618380607,
      "name": 45,
      "tag": "Tadala + Foste Noblado + Mafia",
      "pts": 50,
      "villages": 534535087
    },
    {
      "rank": 126028773,
      "name": 1374,
      "tag": "Azarões do Jogo",
      "pts": 50,
      "villages": 125185939
    },
    {
      "rank": 122032269,
      "name": 190,
      "tag": "T4DALAFILA",
      "pts": 23,
      "villages": 122032269
    },
    {
      "rank": 48121519,
      "name": 95,
      "tag": "TEAM MÁFIA",
      "pts": 10,
      "villages": 48121519
    },
    {
      "rank": 24334681,
      "name": 1417,
      "tag": "TADALA",
      "pts": 1,
      "villages": 24334681
    },
    {
      "rank": 18600380,
      "name": 28,
      "tag": "Foste Noblado",
      "pts": 13,
      "villages": 18600380
    },
    {
      "rank": 2528339,
      "name": 1413,
      "tag": "Vamos Até o Fim",
      "pts": 14,
      "villages": 2528339
    },
    {
      "rank": 1868439,
      "name": 488,
      "tag": "Amigos do Dirceu",
      "pts": 2,
      "villages": 1868439
    },
    {
      "rank": 446840,
      "name": 118,
      "tag": "MÁFIA TEAM",
      "pts": 3,
      "villages": 446840
    },
    {
      "rank": 42819,
      "name": 199,
      "tag": "S U P O R T E!",
      "pts": 3,
      "villages": 42819
    },
    {
      "rank": 21656,
      "name": 876,
      "tag": "Thailand",
      "pts": 13,
      "villages": 21656
    },
    {
      "rank": 70165,
      "name": 170,
      "tag": "Awa Guaj",
      "pts": 1,
      "villages": 70165
    },
    {
      "rank": 10714,
      "name": 1311,
      "tag": "LoGosh O Lobo Fantamas",
      "pts": 2,
      "villages": 10714
    },
    {
      "rank": 531,
      "name": 1114,
      "tag": "VETERANOS TW",
      "pts": 2,
      "villages": 531
    },
    {
      "rank": 71,
      "name": 40,
      "tag": "Fimb",
      "pts": 1,
      "villages": 71
    },
    {
      "rank": 1568,
      "name": 972,
      "tag": "IMPERIO MONGOL",
      "pts": 1,
      "villages": 1568
    },
    {
      "rank": 837,
      "name": 266,
      "tag": "Lachesis muta do Norte",
      "pts": 1,
      "villages": 837
    },
    {
      "rank": 401,
      "name": 353,
      "tag": "RenegadosS",
      "pts": 1,
      "villages": 401
    },
    {
      "rank": 162,
      "name": 1065,
      "tag": "Evolution",
      "pts": 1,
      "villages": 162
    },
    {
      "rank": 1313,
      "name": 1144,
      "tag": "Army Of Death",
      "pts": 1,
      "villages": 1313
    },
    {
      "rank": 2532,
      "name": 1400,
      "tag": "The Lost Men",
      "pts": 1,
      "villages": 2532
    },
    {
      "rank": 3822,
      "name": 1396,
      "tag": "Liga dos Barões",
      "pts": 1,
      "villages": 3822
    }
  ]
}