{
  "players": [
    {
      "rank": 27028640,
      "name": 8092491,
      "pts": 2227,
      "villages": 45
    },
    {
      "rank": 24244066,
      "name": 919837538,
      "pts": 2173,
      "villages": 1417
    },
    {
      "rank": 20022685,
      "name": 919434669,
      "pts": 1530,
      "villages": 45
    },
    {
      "rank": 17724030,
      "name": 6422318,
      "pts": 1438,
      "villages": 45
    },
    {
      "rank": 16837397,
      "name": 7166493,
      "pts": 1347,
      "villages": 45
    },
    {
      "rank": 16429689,
      "name": 1361136,
      "pts": 1372,
      "villages": 45
    },
    {
      "rank": 15927098,
      "name": 919346207,
      "pts": 1320,
      "villages": 45
    },
    {
      "rank": 15807677,
      "name": 919659588,
      "pts": 1364,
      "villages": 45
    },
    {
      "rank": 15496657,
      "name": 919860449,
      "pts": 1315,
      "villages": 45
    },
    {
      "rank": 15479622,
      "name": 6085300,
      "pts": 1244,
      "villages": 45
    },
    {
      "rank": 15297502,
      "name": 919390038,
      "pts": 1214,
      "villages": 45
    },
    {
      "rank": 15000584,
      "name": 919580274,
      "pts": 1258,
      "villages": 45
    },
    {
      "rank": 14456936,
      "name": 7928191,
      "pts": 1208,
      "villages": 45
    },
    {
      "rank": 14281309,
      "name": 919866147,
      "pts": 1307,
      "villages": 45
    },
    {
      "rank": 14280291,
      "name": 919619983,
      "pts": 1197,
      "villages": 45
    },
    {
      "rank": 14036320,
      "name": 919344978,
      "pts": 1191,
      "villages": 45
    },
    {
      "rank": 13917541,
      "name": 919864891,
      "pts": 1177,
      "villages": 45
    },
    {
      "rank": 13346041,
      "name": 919551372,
      "pts": 1150,
      "villages": 45
    },
    {
      "rank": 13189205,
      "name": 919694385,
      "pts": 1106,
      "villages": 45
    },
    {
      "rank": 13129967,
      "name": 171892,
      "pts": 1060,
      "villages": 45
    },
    {
      "rank": 12981032,
      "name": 919783476,
      "pts": 1079,
      "villages": 45
    },
    {
      "rank": 12822537,
      "name": 5495724,
      "pts": 1137,
      "villages": 45
    },
    {
      "rank": 12756125,
      "name": 707128,
      "pts": 1051,
      "villages": 45
    },
    {
      "rank": 12624037,
      "name": 919834361,
      "pts": 1046,
      "villages": 95
    },
    {
      "rank": 12611600,
      "name": 919858565,
      "pts": 1039,
      "villages": 45
    },
    {
      "rank": 12602612,
      "name": 919626659,
      "pts": 1092,
      "villages": 190
    },
    {
      "rank": 12347306,
      "name": 8259125,
      "pts": 1024,
      "villages": 45
    },
    {
      "rank": 12081366,
      "name": 5295749,
      "pts": 983,
      "villages": 45
    },
    {
      "rank": 11998356,
      "name": 919393296,
      "pts": 1023,
      "villages": 45
    },
    {
      "rank": 11919203,
      "name": 919671987,
      "pts": 1023,
      "villages": 190
    },
    {
      "rank": 11854948,
      "name": 918707943,
      "pts": 990,
      "villages": 45
    },
    {
      "rank": 11854832,
      "name": 919623858,
      "pts": 1005,
      "villages": 45
    },
    {
      "rank": 11845990,
      "name": 919685196,
      "pts": 987,
      "villages": 45
    },
    {
      "rank": 11755981,
      "name": 919511204,
      "pts": 1030,
      "villages": 45
    },
    {
      "rank": 11690149,
      "name": 919574579,
      "pts": 1035,
      "villages": 45
    },
    {
      "rank": 11442048,
      "name": 6665293,
      "pts": 1078,
      "villages": 45
    },
    {
      "rank": 11402004,
      "name": 919507006,
      "pts": 1049,
      "villages": 45
    },
    {
      "rank": 11350146,
      "name": 7251297,
      "pts": 974,
      "villages": 95
    },
    {
      "rank": 11066680,
      "name": 919626393,
      "pts": 933,
      "villages": 45
    },
    {
      "rank": 11056448,
      "name": 919453825,
      "pts": 926,
      "villages": 45
    },
    {
      "rank": 10874556,
      "name": 919600011,
      "pts": 897,
      "villages": 45
    },
    {
      "rank": 10328704,
      "name": 2117689,
      "pts": 892,
      "villages": 45
    },
    {
      "rank": 10273122,
      "name": 388517,
      "pts": 851,
      "villages": 190
    },
    {
      "rank": 10001019,
      "name": 919658417,
      "pts": 839,
      "villages": 95
    },
    {
      "rank": 9977954,
      "name": 919655458,
      "pts": 846,
      "villages": 45
    },
    {
      "rank": 9859523,
      "name": 919725219,
      "pts": 992,
      "villages": 45
    },
    {
      "rank": 9852619,
      "name": 5307209,
      "pts": 976,
      "villages": 45
    },
    {
      "rank": 9696783,
      "name": 7942210,
      "pts": 845,
      "villages": 190
    },
    {
      "rank": 9692117,
      "name": 919861757,
      "pts": 819,
      "villages": 190
    },
    {
      "rank": 9460546,
      "name": 6701185,
      "pts": 790,
      "villages": 45
    }
  ],
  "tribes": [
    {
      "rank": 628290317,
      "name": 45,
      "tag": "Tadala + Foste Noblado + Mafia",
      "pts": 50,
      "villages": 544106377
    },
    {
      "rank": 118349025,
      "name": 1374,
      "tag": "Azarões do Jogo",
      "pts": 49,
      "villages": 117636643
    },
    {
      "rank": 132864396,
      "name": 190,
      "tag": "T4DALAFILA",
      "pts": 24,
      "villages": 132864396
    },
    {
      "rank": 49029713,
      "name": 95,
      "tag": "TEAM MÁFIA",
      "pts": 10,
      "villages": 49029713
    },
    {
      "rank": 24244112,
      "name": 1417,
      "tag": "TADALA",
      "pts": 1,
      "villages": 24244112
    },
    {
      "rank": 18703803,
      "name": 28,
      "tag": "Foste Noblado",
      "pts": 13,
      "villages": 18703803
    },
    {
      "rank": 2300332,
      "name": 1413,
      "tag": "Vamos Até o Fim",
      "pts": 14,
      "villages": 2300332
    },
    {
      "rank": 1506365,
      "name": 488,
      "tag": "Amigos do Dirceu",
      "pts": 2,
      "villages": 1506365
    },
    {
      "rank": 121522,
      "name": 199,
      "tag": "S U P O R T E!",
      "pts": 4,
      "villages": 121522
    },
    {
      "rank": 446840,
      "name": 118,
      "tag": "MÁFIA TEAM",
      "pts": 3,
      "villages": 446840
    },
    {
      "rank": 21656,
      "name": 876,
      "tag": "Thailand",
      "pts": 13,
      "villages": 21656
    },
    {
      "rank": 74623,
      "name": 170,
      "tag": "Awa Guaj",
      "pts": 1,
      "villages": 74623
    },
    {
      "rank": 10795,
      "name": 1311,
      "tag": "LoGosh O Lobo Fantamas",
      "pts": 2,
      "villages": 10795
    },
    {
      "rank": 83,
      "name": 40,
      "tag": "Fimb",
      "pts": 1,
      "villages": 83
    },
    {
      "rank": 1677,
      "name": 972,
      "tag": "IMPERIO MONGOL",
      "pts": 1,
      "villages": 1677
    },
    {
      "rank": 837,
      "name": 266,
      "tag": "Lachesis muta do Norte",
      "pts": 1,
      "villages": 837
    },
    {
      "rank": 401,
      "name": 353,
      "tag": "RenegadosS",
      "pts": 1,
      "villages": 401
    },
    {
      "rank": 190,
      "name": 1065,
      "tag": "Evolution",
      "pts": 1,
      "villages": 190
    },
    {
      "rank": 1385,
      "name": 1144,
      "tag": "Army Of Death",
      "pts": 1,
      "villages": 1385
    },
    {
      "rank": 2733,
      "name": 1400,
      "tag": "The Lost Men",
      "pts": 1,
      "villages": 2733
    },
    {
      "rank": 3944,
      "name": 1396,
      "tag": "Liga dos Barões",
      "pts": 1,
      "villages": 3944
    }
  ]
}