{
  "players": [
    {
      "rank": 5790179,
      "name": 561464,
      "pts": 580,
      "villages": 93
    },
    {
      "rank": 5629881,
      "name": 849363286,
      "pts": 603,
      "villages": 407
    },
    {
      "rank": 5041375,
      "name": 11339712,
      "pts": 518,
      "villages": 163
    },
    {
      "rank": 5004190,
      "name": 11125816,
      "pts": 574,
      "villages": 93
    },
    {
      "rank": 4641817,
      "name": 11558274,
      "pts": 506,
      "villages": 93
    },
    {
      "rank": 4508850,
      "name": 11268401,
      "pts": 437,
      "villages": 163
    },
    {
      "rank": 4318507,
      "name": 849280143,
      "pts": 540,
      "villages": 93
    },
    {
      "rank": 4216968,
      "name": 11462716,
      "pts": 429,
      "villages": 163
    },
    {
      "rank": 3939591,
      "name": 849357558,
      "pts": 447,
      "villages": 163
    },
    {
      "rank": 3393432,
      "name": 848883676,
      "pts": 439,
      "villages": 93
    },
    {
      "rank": 3215892,
      "name": 848944967,
      "pts": 310,
      "villages": 163
    },
    {
      "rank": 3038505,
      "name": 8341605,
      "pts": 321,
      "villages": 171
    },
    {
      "rank": 3013544,
      "name": 849382511,
      "pts": 316,
      "villages": 93
    },
    {
      "rank": 2905797,
      "name": 1340513,
      "pts": 333,
      "villages": 163
    },
    {
      "rank": 2886456,
      "name": 849225074,
      "pts": 346,
      "villages": 93
    },
    {
      "rank": 2768014,
      "name": 11172404,
      "pts": 293,
      "villages": 171
    },
    {
      "rank": 2700111,
      "name": 11253348,
      "pts": 331,
      "villages": 163
    },
    {
      "rank": 2690341,
      "name": 849112260,
      "pts": 339,
      "villages": 171
    },
    {
      "rank": 2678711,
      "name": 11166958,
      "pts": 284,
      "villages": 407
    },
    {
      "rank": 2670956,
      "name": 11423926,
      "pts": 328,
      "villages": 163
    },
    {
      "rank": 2533144,
      "name": 11554206,
      "pts": 279,
      "villages": 93
    },
    {
      "rank": 2386923,
      "name": 10177562,
      "pts": 233,
      "villages": 227
    },
    {
      "rank": 2383842,
      "name": 849128004,
      "pts": 247,
      "villages": 163
    },
    {
      "rank": 2336221,
      "name": 849375547,
      "pts": 280,
      "villages": 227
    },
    {
      "rank": 2323345,
      "name": 848899147,
      "pts": 286,
      "villages": 163
    },
    {
      "rank": 2318846,
      "name": 11457342,
      "pts": 265,
      "villages": 227
    },
    {
      "rank": 2186484,
      "name": 849356279,
      "pts": 241,
      "villages": 407
    },
    {
      "rank": 2109425,
      "name": 11444691,
      "pts": 266,
      "villages": 171
    },
    {
      "rank": 2088660,
      "name": 849181920,
      "pts": 245,
      "villages": 163
    },
    {
      "rank": 2080193,
      "name": 11291357,
      "pts": 243,
      "villages": 163
    },
    {
      "rank": 2047644,
      "name": 11461669,
      "pts": 205,
      "villages": 93
    },
    {
      "rank": 1985008,
      "name": 9941625,
      "pts": 248,
      "villages": 93
    },
    {
      "rank": 1984139,
      "name": 1105633,
      "pts": 245,
      "villages": 163
    },
    {
      "rank": 1963096,
      "name": 2819640,
      "pts": 223,
      "villages": 171
    },
    {
      "rank": 1937903,
      "name": 11345880,
      "pts": 225,
      "villages": 163
    },
    {
      "rank": 1787313,
      "name": 10725639,
      "pts": 247,
      "villages": 93
    },
    {
      "rank": 1744066,
      "name": 11134213,
      "pts": 214,
      "villages": 227
    },
    {
      "rank": 1699807,
      "name": 131000,
      "pts": 187,
      "villages": 171
    },
    {
      "rank": 1673099,
      "name": 11550048,
      "pts": 219,
      "villages": 65
    },
    {
      "rank": 1668310,
      "name": 11129135,
      "pts": 195,
      "villages": 163
    },
    {
      "rank": 1612425,
      "name": 10635927,
      "pts": 228,
      "villages": 171
    },
    {
      "rank": 1574349,
      "name": 849202268,
      "pts": 211,
      "villages": 171
    },
    {
      "rank": 1537070,
      "name": 11334933,
      "pts": 168,
      "villages": 93
    },
    {
      "rank": 1536922,
      "name": 849173393,
      "pts": 166,
      "villages": 163
    },
    {
      "rank": 1531059,
      "name": 9735896,
      "pts": 199,
      "villages": 407
    },
    {
      "rank": 1454612,
      "name": 849308152,
      "pts": 262,
      "villages": 93
    },
    {
      "rank": 1444445,
      "name": 1532401,
      "pts": 191,
      "villages": 93
    },
    {
      "rank": 1426637,
      "name": 11458366,
      "pts": 167,
      "villages": 93
    },
    {
      "rank": 1415726,
      "name": 849344064,
      "pts": 270,
      "villages": 705
    },
    {
      "rank": 1411460,
      "name": 8499484,
      "pts": 152,
      "villages": 163
    }
  ],
  "tribes": [
    {
      "rank": 45986302,
      "name": 93,
      "tag": "Adolfsbergsskolan",
      "pts": 18,
      "villages": 45986302
    },
    {
      "rank": 47803911,
      "name": 163,
      "tag": "BoopGate",
      "pts": 18,
      "villages": 47803911
    },
    {
      "rank": 24358519,
      "name": 171,
      "tag": "Imagine TREX",
      "pts": 14,
      "villages": 24358519
    },
    {
      "rank": 22469946,
      "name": 407,
      "tag": "Velociraptors",
      "pts": 18,
      "villages": 22469946
    },
    {
      "rank": 18137956,
      "name": 227,
      "tag": "BaapGate",
      "pts": 16,
      "villages": 18137956
    },
    {
      "rank": 12321081,
      "name": 65,
      "tag": "This Is Fine",
      "pts": 16,
      "villages": 12321081
    },
    {
      "rank": 7962896,
      "name": 213,
      "tag": "Adolfbergs Förskola",
      "pts": 16,
      "villages": 7962896
    },
    {
      "rank": 5485244,
      "name": 705,
      "tag": "Death Squad",
      "pts": 6,
      "villages": 5485244
    },
    {
      "rank": 5331202,
      "name": 783,
      "tag": "Lost Ones",
      "pts": 17,
      "villages": 5331202
    },
    {
      "rank": 5357150,
      "name": 251,
      "tag": "BeepGate",
      "pts": 11,
      "villages": 5357150
    },
    {
      "rank": 3334561,
      "name": 742,
      "tag": "KICK AXE REFORMED",
      "pts": 18,
      "villages": 3334561
    },
    {
      "rank": 4271467,
      "name": 911,
      "tag": "BraveHeart",
      "pts": 12,
      "villages": 4271467
    },
    {
      "rank": 3562692,
      "name": 356,
      "tag": "Everything is Fine",
      "pts": 11,
      "villages": 3562692
    },
    {
      "rank": 1908216,
      "name": 402,
      "tag": "The Blood Of Rome",
      "pts": 18,
      "villages": 1908216
    },
    {
      "rank": 1666183,
      "name": 165,
      "tag": "S.N.O.B.S Empire",
      "pts": 16,
      "villages": 1666183
    },
    {
      "rank": 1739007,
      "name": 700,
      "tag": "CHOSEN",
      "pts": 10,
      "villages": 1739007
    },
    {
      "rank": 1647046,
      "name": 604,
      "tag": "Myrmidon",
      "pts": 15,
      "villages": 1647046
    },
    {
      "rank": 1323823,
      "name": 719,
      "tag": "A Random Sappling",
      "pts": 11,
      "villages": 1323823
    },
    {
      "rank": 1023268,
      "name": 90,
      "tag": "Crunk Aint Dead",
      "pts": 9,
      "villages": 1023268
    },
    {
      "rank": 809532,
      "name": 758,
      "tag": "SPLIE 2.0",
      "pts": 16,
      "villages": 809532
    },
    {
      "rank": 881902,
      "name": 825,
      "tag": "Gentilis Regnum",
      "pts": 16,
      "villages": 881902
    },
    {
      "rank": 627923,
      "name": 710,
      "tag": "Garden",
      "pts": 18,
      "villages": 627923
    },
    {
      "rank": 502667,
      "name": 170,
      "tag": "Oscar",
      "pts": 11,
      "villages": 502667
    },
    {
      "rank": 750893,
      "name": 1095,
      "tag": "ALT.F4",
      "pts": 1,
      "villages": 750893
    },
    {
      "rank": 461518,
      "name": 893,
      "tag": "KICK AXE REFORMED 2",
      "pts": 16,
      "villages": 461518
    },
    {
      "rank": 530871,
      "name": 971,
      "tag": "Rancid",
      "pts": 7,
      "villages": 530871
    },
    {
      "rank": 381119,
      "name": 506,
      "tag": "Ammo For Kings",
      "pts": 14,
      "villages": 381119
    },
    {
      "rank": 349836,
      "name": 511,
      "tag": "SPLIE",
      "pts": 15,
      "villages": 349836
    },
    {
      "rank": 747449,
      "name": 654,
      "tag": "STUPID SEXY MICULL FAN CLUB",
      "pts": 2,
      "villages": 747449
    },
    {
      "rank": 727535,
      "name": 366,
      "tag": "Lets See",
      "pts": 2,
      "villages": 727535
    },
    {
      "rank": 431590,
      "name": 518,
      "tag": "Iron Guard",
      "pts": 17,
      "villages": 431590
    },
    {
      "rank": 282064,
      "name": 1046,
      "tag": "DRUNK",
      "pts": 10,
      "villages": 282064
    },
    {
      "rank": 671646,
      "name": 1081,
      "tag": "Humans Against Monsters",
      "pts": 1,
      "villages": 671646
    },
    {
      "rank": 689427,
      "name": 750,
      "tag": "THE PEACEFUL FARMERS",
      "pts": 3,
      "villages": 689427
    },
    {
      "rank": 454497,
      "name": 781,
      "tag": "Sergeant's Minions",
      "pts": 5,
      "villages": 454497
    },
    {
      "rank": 381299,
      "name": 823,
      "tag": "Gentilius Regnum 2.",
      "pts": 12,
      "villages": 381299
    },
    {
      "rank": 354969,
      "name": 873,
      "tag": "THE LAST OF THE MOHICANS",
      "pts": 7,
      "villages": 354969
    },
    {
      "rank": 228833,
      "name": 859,
      "tag": "BLOW",
      "pts": 15,
      "villages": 228833
    },
    {
      "rank": 222345,
      "name": 268,
      "tag": "KickAxe4",
      "pts": 12,
      "villages": 222345
    },
    {
      "rank": 204675,
      "name": 11,
      "tag": "The Knights of St. Patrick",
      "pts": 17,
      "villages": 204675
    },
    {
      "rank": 213806,
      "name": 345,
      "tag": "Assured Nuclear Destruction",
      "pts": 8,
      "villages": 213806
    },
    {
      "rank": 192482,
      "name": 858,
      "tag": "NordHeim",
      "pts": 12,
      "villages": 192482
    },
    {
      "rank": 179341,
      "name": 854,
      "tag": "Kick Axe Reformed Academy",
      "pts": 9,
      "villages": 179341
    },
    {
      "rank": 170201,
      "name": 1056,
      "tag": "Trails in the sky",
      "pts": 1,
      "villages": 170201
    },
    {
      "rank": 153420,
      "name": 25,
      "tag": "Bodyguard",
      "pts": 15,
      "villages": 153420
    },
    {
      "rank": 120617,
      "name": 622,
      "tag": "Do or Die?",
      "pts": 15,
      "villages": 120617
    },
    {
      "rank": 107522,
      "name": 952,
      "tag": "Brewmasters",
      "pts": 16,
      "villages": 107522
    },
    {
      "rank": 110167,
      "name": 191,
      "tag": "The Dark Knight",
      "pts": 11,
      "villages": 110167
    },
    {
      "rank": 111097,
      "name": 1060,
      "tag": "Orgolio",
      "pts": 5,
      "villages": 111097
    },
    {
      "rank": 91868,
      "name": 181,
      "tag": "Canada",
      "pts": 14,
      "villages": 91868
    }
  ]
}